django_profiling_dashboard-0.2.dist-info/DESCRIPTION.rst
django_profiling_dashboard-0.2.dist-info/METADATA
django_profiling_dashboard-0.2.dist-info/metadata.json
django_profiling_dashboard-0.2.dist-info/pbr.json
django_profiling_dashboard-0.2.dist-info/RECORD
django_profiling_dashboard-0.2.dist-info/top_level.txt
django_profiling_dashboard-0.2.dist-info/WHEEL
profiling_dashboard/__init__.py
profiling_dashboard/forms.py
profiling_dashboard/stats.py
profiling_dashboard/urls.py
profiling_dashboard/views.py
profiling_dashboard/static/profiling_dashboard/css/bootstrap.min.css
profiling_dashboard/templates/profiling_dashboard/base.html
profiling_dashboard/templates/profiling_dashboard/cpu.html
profiling_dashboard/templates/profiling_dashboard/memory.html
profiling_dashboard/templates/profiling_dashboard/process_info.html
profiling_dashboard/templates/profiling_dashboard/web_top.html
